test/__init__.py
test/integration_test/__init__.py
test/integration_test/_test_utils.py
test/integration_test/test_MeasurementSpaceTimePoints.py
test/integration_test/test_block_cholesky_decomposition_2D.py
test/integration_test/test_block_cholesky_loglikelihood_2D.py
test/integration_test/test_cholesky_loglikelihood_1D.py
test/integration_test/test_general_loglikelihood.py
test/integration_test/test_kronecker_loglikelihood.py
test/unit_test/__init__.py
test/unit_test/test_utils.py
tripy/__init__.py
tripy/base.py
tripy/kernels.py
tripy/loglikelihood.py
tripy/sampling.py
tripy/utils.py
tri_py-0.9.0.dist-info/LICENCE
tri_py-0.9.0.dist-info/METADATA
tri_py-0.9.0.dist-info/WHEEL
tri_py-0.9.0.dist-info/top_level.txt
tri_py-0.9.0.dist-info/RECORD
