Metadata-Version: 2.1
Name: tri-py
Version: 0.9.0
Summary: A package for efficient loglikelihood evaluation with structured covariance matrices
Home-page: https://gitlab.com/GKoune/tripy
Author: Ioannis Koune
Author-email: G.Koune@gmail.com
Classifier: Programming Language :: Python :: 3
Classifier: License :: OSI Approved :: MIT License
Classifier: Operating System :: OS Independent
Requires-Python: >=3.6
License-File: LICENCE
Requires-Dist: numpy (<2)
Requires-Dist: scipy (<2)
Requires-Dist: nestle (<1)
Requires-Dist: emcee (<4)
Requires-Dist: dynesty (<2)
Requires-Dist: matplotlib (<4)
Requires-Dist: tabulate (<1)
Requires-Dist: tqdm (<5)
Requires-Dist: numba (<1)
Provides-Extra: development
Requires-Dist: six ; extra == 'development'
Requires-Dist: sphinx (<5) ; extra == 'development'
Requires-Dist: sphinx-copybutton (<1) ; extra == 'development'
Requires-Dist: sphinx-inline-tabs ; extra == 'development'
Requires-Dist: sphinxcontrib-bibtex (<3) ; extra == 'development'
Requires-Dist: myst-parser (<1) ; extra == 'development'
Requires-Dist: sphinx-rtd-theme (<2) ; extra == 'development'
Requires-Dist: sphinx-rtd-dark-mode (<2) ; extra == 'development'
Requires-Dist: sphinx-gallery (<1) ; extra == 'development'
Requires-Dist: pytest ; extra == 'development'
Requires-Dist: coverage ; extra == 'development'
Requires-Dist: torch (<2) ; extra == 'development'
Requires-Dist: twine ; extra == 'development'
Requires-Dist: pre-commit ; extra == 'development'
Requires-Dist: black ; extra == 'development'
Requires-Dist: flake8 ; extra == 'development'
Requires-Dist: flake8-tidy-imports ; extra == 'development'
Requires-Dist: flake8-import-order ; extra == 'development'
Provides-Extra: docs
Requires-Dist: six ; extra == 'docs'
Requires-Dist: sphinx (<5) ; extra == 'docs'
Requires-Dist: sphinx-copybutton (<1) ; extra == 'docs'
Requires-Dist: sphinx-inline-tabs ; extra == 'docs'
Requires-Dist: sphinxcontrib-bibtex (<3) ; extra == 'docs'
Requires-Dist: myst-parser (<1) ; extra == 'docs'
Requires-Dist: sphinx-rtd-theme (<2) ; extra == 'docs'
Requires-Dist: sphinx-rtd-dark-mode (<2) ; extra == 'docs'
Requires-Dist: sphinx-gallery (<1) ; extra == 'docs'
Provides-Extra: testing
Requires-Dist: pytest ; extra == 'testing'
Requires-Dist: coverage ; extra == 'testing'
Requires-Dist: torch (<2) ; extra == 'testing'
